setup.py
gpt2/__init__.py
gpt2/modeling.py
pytorch_gpt2.egg-info/PKG-INFO
pytorch_gpt2.egg-info/SOURCES.txt
pytorch_gpt2.egg-info/dependency_links.txt
pytorch_gpt2.egg-info/requires.txt
pytorch_gpt2.egg-info/top_level.txt